steamback/__init__.py
steamback/__main__.py
steamback/gui.py
steamback/test.py
steamback/util.py
steamback/data/icons8-refresh-96.png
steamback-0.3.6.dist-info/LICENSE
steamback-0.3.6.dist-info/METADATA
steamback-0.3.6.dist-info/WHEEL
steamback-0.3.6.dist-info/entry_points.txt
steamback-0.3.6.dist-info/top_level.txt
steamback-0.3.6.dist-info/RECORD
