Metadata-Version: 2.1
Name: steamback
Version: 0.3.6
Summary: A python library and tool for backing up Steam save games
Author-email: Kevin Hester <kevinh@geeksville.com>
Project-URL: Homepage, https://github.com/geeksville/steamback
Project-URL: Bug Tracker, https://github.com/geeksville/steamback/issues
Classifier: Programming Language :: Python :: 3
Classifier: License :: OSI Approved :: GNU General Public License v3 or later (GPLv3+)
Classifier: Operating System :: OS Independent
Requires-Python: >=3.7
License-File: LICENSE
Requires-Dist: platformdirs (~=3.1.0)
Requires-Dist: psutil (~=5.9.1)
Requires-Dist: async-tkinter-loop (~=0.7.0)
Requires-Dist: sv-ttk (~=2.4)
Requires-Dist: timeago (~=1.0.16)
Requires-Dist: Pillow (~=9.2.0)
